assignment_2/data_memory_my.v


`timescale 1ns / 1ps
module data_memory_my #(
    parameter WIDTH = 32,             
    parameter DEPTH = 256             // 256 words = 1KB
)(
    input  wire        clk,
    input  wire        mem_write_en,  
    input  wire [31:0] addr,          
    input  wire [31:0] write_data,    
    output wire [31:0] read_data    
);
    reg [WIDTH-1:0] ram [0:DEPTH-1];
    
    assign read_data = ram[addr[31:2]];  // 
   
    always @(posedge clk) begin
        if (mem_write_en)
            ram[addr[31:2]] <= write_data;  
    end
endmodule

assignment_1/alu_my.v
// goal : Homework: Finish the ALU by using +, -, %, *, AND, OR  by yourself 

`timescale 1ns /1ps
module alu_my (
    input wire [31:0] A,  //input A
    input wire [31:0] B, //input B
    input wire [2:0] alu_oper, //operater select
    output reg [31:0] result, //result
    output wire zero  //zero flag
);
    always @(*) begin
        case (alu_oper)
            3'b000: result = A + B; //add
            3'b001: result = A - B; //sub
            3'b010: result = A / B; //divide
            3'b011: result = A * B; //Multiplier
            3'b100: result = A & B; //AND
            3'b110: result = A | B; //OR
            default: result = 32'd0;
        endcase
    end
    assign zero = (result == 32'd0);
endmodule

assignment_2/reg_file_my.v
`timescale 1ns / 1ps
module reg_file_my (
    input  wire        clk,        // clock
    input  wire        we3,        // write enable
    input  wire [4:0]  wa3,        // write address
    input  wire [31:0] wd3,        // write data
    input  wire [4:0]  ra1,        // read address 1
    input  wire [4:0]  ra2,        // read address 2
    output wire [31:0] rd1,        // read data 1
    output wire [31:0] rd2         // read data 2
);
    reg [31:0] rf [31:0];          // 32 registers x 32 bits
    
    always @(posedge clk) begin
        if (we3 && (wa3 != 5'd0))  // write if enabled, skip $0
            rf[wa3] <= wd3;        // write to register
    end
    
    assign rd1 = (ra1 == 5'd0) ? 32'd0 : rf[ra1];  // $0 always 0
    assign rd2 = (ra2 == 5'd0) ? 32'd0 : rf[ra2];  // $0 always 0
endmodule

assignment_2/instruction_memory_my.v
`timescale 1ns / 1ps

module instruction_memory_my #(
    parameter WIDTH = 32,
    parameter DEPTH = 256   
)(
    input  wire [31:0] addr,       // byte address
    output wire [31:0] rd          // instruction
);
    reg [WIDTH-1:0] ram [0:DEPTH-1];
    
    initial begin 
        $readmemh("memfile.dat", ram);  
    end
    
    assign rd = ram[addr[31:2]];   // word aligned
endmodule

assignment_2/pc_my.v
`timescale 1ns / 1ps
module pc_my (
    input  wire        clk,
    input  wire        rst_n,      // async reset (active low)
    input  wire [31:0] pc_next,    // next PC value
    output reg  [31:0] pc          // current PC
);
    always @(posedge clk or negedge rst_n) begin
        if (!rst_n)
            pc <= 32'd0;           // reset to 0
        else
            pc <= pc_next;         // update PC
    end
endmodule

assignment_2/if_stage_my.v

`timescale 1ns / 1ps
module if_stage_my (
    input  wire        clk,
    input  wire        rst_n,
    output wire [31:0] instr,        // fetched instruction
    output wire [31:0] current_pc    // current PC value
);
    wire [31:0] pc;
    wire [31:0] pc_next;
    
    pc_my u_pc ( 
        .clk(clk),
        .rst_n(rst_n),
        .pc_next(pc_next),
        .pc(pc)
    );
    
    assign pc_next = pc + 32'd4;    
    
    instruction_memory_my u_imem ( 
        .addr(pc),
        .rd(instr)
    );
    
    assign current_pc = pc;          // debug output
endmodule

assignment_2/datapath_my.v
`timescale 1ns / 1ps

module datapath_my (
    input  wire        clk,
    input  wire        rst_n,
    // Control Signals (Driven by TB or Controller)
    input  wire        reg_write_en,   // enable writing to register file
    input  wire        reg_dst,        // select destination register: 0=rt, 1=rd
    input  wire        alu_src,        // select ALU second operand: 0=reg, 1=imm
    input  wire [2:0]  alu_ctrl,       // ALU operation selection
    input  wire        mem_write_en,   // enable writing to data memory (sw)
    input  wire        mem_to_reg,     // select write-back source: 0=ALU, 1=mem
    
    output wire [31:0] pc_out,         // current program counter for debug
    output wire [31:0] alu_result      // current ALU result for debug
);
    // Internal Interconnects
    wire [31:0] instr;                 // raw instruction from memory
    wire [31:0] pc;                    // internal PC value
    wire [31:0] rd1, rd2;              // outputs from register file
    wire [31:0] result;                // final data to write back to reg file
    wire [31:0] read_data;             // data loaded from memory
    wire [31:0] src_b;                 // second operand for ALU
    wire [4:0]  write_reg;             // selected destination register address
    wire [31:0] sign_imm;              // 32-bit sign-extended immediate
    wire        zero_flag;             // unused in Week 4, used for branches later

    // 1. Instruction Fetch Stage
    if_stage_my u_if_stage (
        .clk(clk),
        .rst_n(rst_n),
        .instr(instr),                 // output fetched machine code 
        .current_pc(pc)                // output current PC 
    );
    assign pc_out = pc;

    // 2. Decode Stage & Register File 
    // Mux for Destination Register (rt or rd field)
    assign write_reg = (reg_dst) ? instr[15:11] : instr[20:16];
    
    reg_file_my u_reg_file ( 
        .clk(clk),
        .we3(reg_write_en),
        .ra1(instr[25:21]),            // rs field
        .ra2(instr[20:16]),            // rt field
        .wa3(write_reg),               // write destination
        .wd3(result),                  // data to write
        .rd1(rd1),                     // output operand A
        .rd2(rd2)                      // output operand B
    );

    // Sign Extension for I-type instructions 
   
    assign sign_imm = {{16{instr[15]}}, instr[15:0]};

    // 3. Execution Stage (ALU) 
    // Mux for ALU Source (Register or Immediate)
    assign src_b = (alu_src) ? sign_imm : rd2;
    
    alu_my u_alu ( 
        .A(rd1),
        .B(src_b),
        .alu_oper(alu_ctrl),
        .result(alu_result),
        .zero(zero)
    );

    // 4. Data Memory Stage
    data_memory_my u_data_mem ( 
        .clk(clk),
        .mem_write_en(mem_write_en),
        .addr(alu_result),             // ALU result used as memory address
        .write_data(rd2),              // register rd2 used for store (sw)
        .read_data(read_data)          // data fetched from memory (lw)
    );

    // 5. Write-Back Stage
    // Mux for Data to Register File (Memory contents or ALU result)
    assign result = (mem_to_reg) ? read_data : alu_result;
  

endmodule

assignment_2/datapath_my_tb.v
`timescale 1ns / 1ps

//-----------------------------------------------------------------------------
// Datapath Testbench
// 
// This testbench manually provides control signals to verify the datapath
// behavior. In a complete CPU, these signals would come from the control unit.
//
// Test Program (memfile.dat):
//   20080005 - addi $t0, $zero, 5    → $t0 = 5
//   2009000A - addi $t1, $zero, 10   → $t1 = 10
//   01095020 - add  $t2, $t0, $t1    → $t2 = 5 + 10 = 15
//   AC0A0004 - sw   $t2, 4($zero)    → Mem[4] = $t2
//-----------------------------------------------------------------------------

module datapath_my_tb;

    //-------------------------------------------------------------------------
    // Signal Declarations
    //-------------------------------------------------------------------------
    
    // Clock and Reset
    reg clk;                    // System clock
    reg rst_n;                  // Active-low reset
    
    // Control Signals (manually provided in this testbench)
    reg reg_write_en;           // Enable write to register file
    reg reg_dst;                // Destination register select: 0=rt, 1=rd
    reg alu_src;                // ALU source B select: 0=register, 1=immediate
    reg [2:0] alu_ctrl;         // ALU operation: 010=ADD, 110=SUB, etc.
    reg mem_write_en;           // Enable write to data memory
    reg mem_to_reg;             // Write-back source: 0=ALU result, 1=memory data
    
    // Output Signals
    wire [31:0] pc_out;         // Current program counter value
    wire [31:0] alu_result;     // ALU computation result

    //-------------------------------------------------------------------------
    // Device Under Test (DUT) Instantiation
    //-------------------------------------------------------------------------
    datapath_my uut (
        .clk(clk),
        .rst_n(rst_n),
        .reg_write_en(reg_write_en),
        .reg_dst(reg_dst),
        .alu_src(alu_src),
        .alu_ctrl(alu_ctrl),
        .mem_write_en(mem_write_en),
        .mem_to_reg(mem_to_reg),
        .pc_out(pc_out),
        .alu_result(alu_result)
    );

    //-------------------------------------------------------------------------
    // Clock Generation: 10ns period (100MHz)
    //-------------------------------------------------------------------------
    initial begin
        clk = 0;
        forever #5 clk = ~clk;  // Toggle every 5ns → 10ns period
    end

    //-------------------------------------------------------------------------
    // Waveform Dump for GTKWave
    //-------------------------------------------------------------------------
    initial begin
        $dumpfile("datapath_my.vcd");
        $dumpvars(0, datapath_my_tb);
    end

    //-------------------------------------------------------------------------
    // Test Sequence
    //-------------------------------------------------------------------------
    initial begin
        //---------------------------------------------------------------------
        // Initialize: Reset all signals
        //---------------------------------------------------------------------
        rst_n = 0;                          // Assert reset (active-low)
        reg_write_en = 0; 
        reg_dst = 0; 
        alu_src = 0; 
        alu_ctrl = 0; 
        mem_write_en = 0; 
        mem_to_reg = 0;
        #10;                                // Wait 10ns
        rst_n = 1;                          // Release reset
        $display("--- Start Simulation ---");

        //---------------------------------------------------------------------
        // Instruction 1: addi (I-Type)
        // Instruction: addi $t0, $zero, 7   →  $t0 = 7
        // Control: reg_write=1, alu_src=1(immediate), alu_ctrl=ADD, reg_dst=0(rt)
        // Expected: $t0 = 0 + 7 = 7
        //---------------------------------------------------------------------
        reg_write_en = 1;                   // Enable register write
        alu_src = 1;                        // ALU source B = sign-extended immediate
        alu_ctrl = 3'b000;                  // ALU operation = ADD
        reg_dst = 0;                        // Destination = rt (I-Type)
        mem_write_en = 0;                   // No memory write
        #2; 
        $display("PC: %h | Result: %d (Expected 7)", pc_out, alu_result);
        @(posedge clk);                     // Wait for clock edge
        
        //---------------------------------------------------------------------
        // Instruction 2: addi (I-Type)  
        // Instruction: addi $t1, $zero, 3   →  $t1 = 3
        // Expected: $t1 = 0 + 3 = 3
        //---------------------------------------------------------------------
        #1; 
        reg_write_en = 1;
        alu_src = 1;
        alu_ctrl = 3'b000;
        reg_dst = 0;
        mem_write_en = 0;
        #2;
        $display("PC: %h | Result: %d (Expected 3)", pc_out, alu_result);
        @(posedge clk);
        
        //---------------------------------------------------------------------
        // Instruction 3: sub (R-Type)
        // Instruction: sub  $t2, $t0, $t1   →  $t2 = 7 - 3 = 4
        // Control: reg_write=1, alu_src=0(register), alu_ctrl=sub, reg_dst=1(rd)
        // Expected: $t2 = $t0 + $t1 = 7 - 3 = 4
        //---------------------------------------------------------------------
        #1;
        reg_write_en = 1;
        alu_src = 0;                        // ALU source B = register (rd2)
        alu_ctrl = 3'b001;                  // ALU operation = sub
        reg_dst = 1;                        // Destination = rd (R-Type)
        mem_write_en = 0;
        #2;
        $display("PC: %h | Result: %d (Expected 4)", pc_out, alu_result);
        @(posedge clk);
        
        
        //---------------------------------------------------------------------
        // End Simulation
        //---------------------------------------------------------------------
        #20;
        $finish;
    end

endmodule

assignment_2/datapath_my.vcd
$date
	Fri Apr 10 10:26:53 2026
$end
$version
	Icarus Verilog
$end
$timescale
	1ps
$end
$scope module datapath_my_tb $end
$var wire 32 ! pc_out [31:0] $end
$var wire 32 " alu_result [31:0] $end
$var reg 3 # alu_ctrl [2:0] $end
$var reg 1 $ alu_src $end
$var reg 1 % clk $end
$var reg 1 & mem_to_reg $end
$var reg 1 ' mem_write_en $end
$var reg 1 ( reg_dst $end
$var reg 1 ) reg_write_en $end
$var reg 1 * rst_n $end
$scope module uut $end
$var wire 3 + alu_ctrl [2:0] $end
$var wire 1 $ alu_src $end
$var wire 1 % clk $end
$var wire 1 & mem_to_reg $end
$var wire 1 ' mem_write_en $end
$var wire 32 , pc_out [31:0] $end
$var wire 1 ( reg_dst $end
$var wire 1 ) reg_write_en $end
$var wire 1 * rst_n $end
$var wire 1 - zero $end
$var wire 5 . write_reg [4:0] $end
$var wire 32 / src_b [31:0] $end
$var wire 32 0 sign_imm [31:0] $end
$var wire 32 1 result [31:0] $end
$var wire 32 2 read_data [31:0] $end
$var wire 32 3 rd2 [31:0] $end
$var wire 32 4 rd1 [31:0] $end
$var wire 32 5 pc [31:0] $end
$var wire 32 6 instr [31:0] $end
$var wire 32 7 alu_result [31:0] $end
$scope module u_alu $end
$var wire 32 8 B [31:0] $end
$var wire 3 9 alu_oper [2:0] $end
$var wire 1 - zero $end
$var wire 32 : A [31:0] $end
$var reg 32 ; result [31:0] $end
$upscope $end
$scope module u_data_mem $end
$var wire 32 < addr [31:0] $end
$var wire 1 % clk $end
$var wire 1 ' mem_write_en $end
$var wire 32 = read_data [31:0] $end
$var wire 32 > write_data [31:0] $end
$var parameter 32 ? DEPTH $end
$var parameter 32 @ WIDTH $end
$upscope $end
$scope module u_if_stage $end
$var wire 1 % clk $end
$var wire 32 A current_pc [31:0] $end
$var wire 1 * rst_n $end
$var wire 32 B pc_next [31:0] $end
$var wire 32 C pc [31:0] $end
$var wire 32 D instr [31:0] $end
$scope module u_imem $end
$var wire 32 E rd [31:0] $end
$var wire 32 F addr [31:0] $end
$var parameter 32 G DEPTH $end
$var parameter 32 H WIDTH $end
$upscope $end
$scope module u_pc $end
$var wire 1 % clk $end
$var wire 32 I pc_next [31:0] $end
$var wire 1 * rst_n $end
$var reg 32 J pc [31:0] $end
$upscope $end
$upscope $end
$scope module u_reg_file $end
$var wire 1 % clk $end
$var wire 5 K ra1 [4:0] $end
$var wire 5 L ra2 [4:0] $end
$var wire 5 M wa3 [4:0] $end
$var wire 32 N wd3 [31:0] $end
$var wire 1 ) we3 $end
$var wire 32 O rd2 [31:0] $end
$var wire 32 P rd1 [31:0] $end
$upscope $end
$upscope $end
$upscope $end
$enddefinitions $end
$comment Show the parameter values. $end
$dumpall
b100000 H
b100000000 G
b100000 @
b100000000 ?
$end
#0
$dumpvars
b0 P
bx O
bx N
b1000 M
b1000 L
b0 K
b0 J
b100 I
b0 F
b100000000010000000000000000111 E
b100000000010000000000000000111 D
b0 C
b100 B
b0 A
bx >
bx =
bx <
bx ;
b0 :
b0 9
bx 8
bx 7
b100000000010000000000000000111 6
b0 5
b0 4
bx 3
bx 2
bx 1
b111 0
bx /
b1000 .
x-
b0 ,
b0 +
0*
0)
0(
0'
0&
0%
0$
b0 #
bx "
b0 !
$end
#5000
1%
#10000
b111 1
b111 N
0-
b111 "
b111 7
b111 ;
b111 <
b111 /
b111 8
0%
1$
1)
1*
#15000
b11 1
b11 N
b11 "
b11 7
b11 ;
b11 <
b11 /
b11 8
b1001 .
b1001 M
b11 0
b1001 L
bx 3
bx >
bx O
b100000000010010000000000000011 6
b100000000010010000000000000011 D
b100000000010010000000000000011 E
b1000 B
b1000 I
b100 !
b100 ,
b100 5
b100 A
b100 C
b100 F
b100 J
1%
#20000
0%
#25000
b101000000101001 1
b101000000101001 N
b101000000101001 "
b101000000101001 7
b101000000101001 ;
b101000000101001 <
b101000000100010 /
b101000000100010 8
b111 4
b111 :
b111 P
b101000000100010 0
b1000 K
b11 3
b11 >
b11 O
b1000010010101000000100010 6
b1000010010101000000100010 D
b1000010010101000000100010 E
b1100 B
b1100 I
b1000 !
b1000 ,
b1000 5
b1000 A
b1000 C
b1000 F
b1000 J
1%
#26000
b100 1
b100 N
b1010 .
b1010 M
b100 "
b100 7
b100 ;
b100 <
b11 /
b11 8
1(
b1 #
b1 +
b1 9
0$
#30000
0%
#35000
bx 1
bx N
bx /
bx 8
x-
bx "
bx 7
bx ;
bx <
bx 3
bx >
bx O
bx 4
bx :
bx P
bx .
bx M
bx 0
bx L
bx K
bx 6
bx D
bx E
b10000 B
b10000 I
b1100 !
b1100 ,
b1100 5
b1100 A
b1100 C
b1100 F
b1100 J
1%
#40000
0%
#45000
b10100 B
b10100 I
b10000 !
b10000 ,
b10000 5
b10000 A
b10000 C
b10000 F
b10000 J
1%
#50000
0%
#55000
b11000 B
b11000 I
b10100 !
b10100 ,
b10100 5
b10100 A
b10100 C
b10100 F
b10100 J
1%
